[
    {
        "id": "diary-20251014",
        "date": "2025-10-14",
        "title": "财务系统优化+精力补充",
        "category": "学习成长",
        "content": "阅读10本书+。\n持续搭建个人网站,加了N个功能+自我介绍网站+......\n优化原始财务系统表。\n学习11小时+。",
        "achievement": "RSS订阅搭建",
        "reflection": "",
        "tags": ["学习", "创作"],
        "achievementLevel": 1
    },
    {
        "id": "diary-20251013",
        "date": "2025-10-13",
        "title": "财务系统优化+精力补充",
        "category": "学习成长",
        "content": "阅读10本书+。\n持续搭建个人网站,\"成功日记\"中英互换功能优化+英文Emoji优化+英文左对齐。\n优化原始财务系统表。\n学习8小时+。\n反刍了近500个收集的\"今日有价值的互动\"",
        "achievement": "RSS订阅搭建",
        "reflection": "",
        "tags": ["学习", "创作"],
        "achievementLevel": 1
    },
    {
        "id": "diary-20251012",
        "date": "2025-10-12",
        "title": "读完《专注的真相》+前哨战财务系统优化",
        "category": "学习成长",
        "content": "阅读10本书+。\n持续搭建个人网站,加了背景壁纸。\n早起+去图书馆+读完《专注的真相》+优化原始时间负债表。\n学习14小时+",
        "achievement": "公众号一天创作了3篇文稿；以项目为导向的学习，写完了教材大纲",
        "reflection": "",
        "tags": ["学习", "创作", "音乐"],
        "achievementLevel": 3
    },
    {
        "id": "diary-20251011",
        "date": "2025-10-11",
        "title": "早起+去图书馆",
        "category": "学习成长",
        "content": "阅读10本书+。\n持续搭建个人网站,加了\"成功日记一键回到顶部的功能\"。\n专注比80%。\n学习14小时+",
        "achievement": "遇到两只小狗可爱😊；图书馆天气好",
        "reflection": "",
        "tags": ["学习", "影视", "创作"],
        "achievementLevel": 5
    },
    {
        "id": "diary-20251010",
        "date": "2025-10-10",
        "title": "阅读+早睡",
        "category": "学习成长",
        "content": "阅读10本书+。\n持续搭建个人网站,修改阅读室错别字+修复了没有显示的bug+补充成功日记的成就值+成功日记Emoji优化。\n睡眠充足。\n学习10小时+",
        "achievement": "罗永浩*Tim播客不错",
        "reflection": "",
        "tags": ["学习", "影视", "创作"],
        "achievementLevel": 3
    },
    {
        "id": "diary-20251009",
        "date": "2025-10-09",
        "title": "阅读+产品测试",
        "category": "学习成长",
        "content": "阅读10本书+。\n产品在淘宝闲鱼测试。\n持续搭建个人网站,补充了启发值。\n睡眠充足。\n学习14小时+",
        "achievement": "前哨战关于时间负债的实操👍",
        "reflection": "",
        "tags": ["学习", "影视", "创作"],
        "achievementLevel": 4
    },
    {
        "id": "diary-20251008",
        "date": "2025-10-08",
        "title": "阅读+产品测试",
        "category": "学习成长",
        "content": "阅读10本书+且读完《区块链革命》。\n产品在淘宝闲鱼测试。\n持续搭建个人网站,加了一键回到顶部的功能。\n睡眠充足。\n学习14小时+",
        "achievement": "榴莲不错;罗永浩×TIM双厨狂喜",
        "reflection": "",
        "tags": ["学习", "影视", "创作"],
        "achievementLevel": 4
    },
    {
        "id": "diary-20251007",
        "date": "2025-10-07",
        "title": "阅读+产品测试",
        "category": "学习成长",
        "content": "阅读10本书+。\n产品在淘宝闲鱼测试。\n持续搭建个人网站,加了背景。\n睡眠充足。\n学习7小时+",
        "achievement": "寿司不错😌;凡人修仙传不错",
        "reflection": "",
        "tags": ["学习", "影视", "创作"],
        "achievementLevel": 1
    },
    {
        "id": "diary-20251006",
        "date": "2025-10-06",
        "title": "阅读+产品测试",
        "category": "学习成长",
        "content": "阅读10本书+。\n产品在淘宝闲鱼测试。\n持续搭建个人网站,加了背景。\n睡眠充足。\n学习10小时+",
        "achievement": "椰子水不错😌",
        "reflection": "",
        "tags": ["学习", "创作"],
        "achievementLevel": 4
    },
    {
        "id": "diary-20251005",
        "date": "2025-10-05",
        "title": "阅读+前哨战\"以项目为导向\"",
        "category": "学习成长",
        "content": "阅读10本书+。\n写产品商业书。\n持续搭建个人网站。\n睡眠充足。",
        "achievement": "Linksphotograph的视频\"在世界上最孤独的房子里过一夜!\"好看",
        "reflection": "",
        "tags": ["学习", "影视", "创作"],
        "achievementLevel": 2
    },
    {
        "id": "diary-20251001",
        "date": "2025-10-01",
        "title": "打造朋友圈数字花园",
        "category": "工作学习",
        "content": "坚持 7 小时深度学习并上线个人朋友圈站点。",
        "achievement": "《回家的路》真的很好听 🌌",
        "reflection": "",
        "tags": ["工作", "学习", "创作"],
        "achievementLevel": 1
    },
    {
        "id": "diary-20251004",
        "date": "2025-10-04",
        "title": "图书馆深耕与网站焕新",
        "category": "学习成长",
        "content": "去图书馆学习。\n网站整体翻新迭代。\n学习12个小时+。",
        "achievement": "影视飓风 1300 万粉丝评论区的 BGM 切画面经验值得学习。",
        "reflection": "",
        "tags": ["学习", "创作"],
        "achievementLevel": 3
    },
    {
        "id": "diary-20251003",
        "date": "2025-10-03",
        "title": "提前完成阅读记录并整理电脑",
        "category": "阅读学习",
        "content": "提前完成今日阅读记录。\n梳理并整理电脑内容。",
        "achievement": "双影奇境依旧很好玩 😄",
        "reflection": "",
        "tags": ["阅读", "学习"],
        "achievementLevel": 1
    },
    {
        "id": "diary-20251002",
        "date": "2025-10-02",
        "title": "读完《小狗钱钱》",
        "category": "工作学习",
        "content": "完成阅读笔记并沉浸于双影奇境的奇妙体验。",
        "achievement": "双影奇境不错 😄",
        "reflection": "",
        "tags": ["工作", "学习", "自然"],
        "achievementLevel": 1
    },
    {
        "id": "diary-20250930",
        "date": "2025-09-30",
        "title": "超额完成 10 小时专注学习",
        "category": "学习成长",
        "content": "图书馆学习氛围满分,提前完成阅读任务。",
        "achievement": "图书馆学习真不错 ٩(•̤̀ᵕ•̤́๑)ᵒᵏᵎᵎᵎᵎ",
        "reflection": "",
        "tags": ["工作", "学习", "健身", "自然"],
        "achievementLevel": 3
    },
    {
        "id": "diary-20250929",
        "date": "2025-09-29",
        "title": "拥抱清晨,完成每日收官",
        "category": "阅读健身",
        "content": "七小时高效心流,计划全部按时完成。",
        "achievement": "收录了两条人生启示录。",
        "reflection": "",
        "tags": ["阅读", "健身"],
        "achievementLevel": 3
    },
    {
        "id": "diary-20250928",
        "date": "2025-09-28",
        "title": "十本书与课程交付的前哨战",
        "category": "学习健身",
        "content": "成功读完十本书。\n提交 Rising Tide 课程(虽只录了四节)。\n保持活力训练。",
        "achievement": "睡眠充足;前哨战;猕猴桃不错 😋",
        "reflection": "",
        "tags": ["学习", "健身"],
        "achievementLevel": 1
    },
    {
        "id": "diary-20250927",
        "date": "2025-09-27",
        "title": "十本书与两部作品",
        "category": "学习成长",
        "content": "成功阅读十本书。\n创作两部影像作品。",
        "achievement": "睡眠充足,状态在线。",
        "reflection": "",
        "tags": ["学习"],
        "achievementLevel": 1
    },
    {
        "id": "diary-20250926",
        "date": "2025-09-26",
        "title": "图书馆深度学习日",
        "category": "学习成长",
        "content": "专程前往图书馆学习,保持高效节奏。",
        "achievement": "图书馆学习氛围一如既往的好。",
        "reflection": "",
        "tags": ["学习", "自然"],
        "achievementLevel": 1
    },
    {
        "id": "diary-20250925",
        "date": "2025-09-25",
        "title": "阅读九本书与作品发布",
        "category": "阅读创作",
        "content": "阅读九本书。\n发布两部视频作品。",
        "achievement": "罗永浩 × 西门子的内容带来灵感。",
        "reflection": "",
        "tags": ["阅读", "创作"],
        "achievementLevel": 1
    },
    {
        "id": "diary-20250924",
        "date": "2025-09-24",
        "title": "九本书与公众号文章输出",
        "category": "阅读影视",
        "content": "一天读完九本书并输出成公众号文章。",
        "achievement": "罗永浩 × 周鸿祎 3 小时播客双厨狂喜。",
        "reflection": "",
        "tags": ["阅读", "影视"],
        "achievementLevel": 1
    },
    {
        "id": "diary-20250923",
        "date": "2025-09-23",
        "title": "山川与自然疗愈日",
        "category": "旅行自然",
        "content": "出行感受自然,给自己放个假。",
        "achievement": "",
        "reflection": "",
        "tags": ["旅行", "自然"],
        "achievementLevel": 1
    },
    {
        "id": "diary-20250922",
        "date": "2025-09-22",
        "title": "《真需求》与自动化工作流",
        "category": "阅读学习",
        "content": "读完《真需求》。\n阅读 7 本书并完成输出。\n打造小程序自动化工作流。\n早睡并坚持体能训练。\n控制每日开销 15 元。",
        "achievement": "",
        "reflection": "",
        "tags": ["阅读", "学习", "健身"],
        "achievementLevel": 1
    },
    {
        "id": "diary-20250921",
        "date": "2025-09-21",
        "title": "电影清单清空与十篇初稿",
        "category": "学习工作",
        "content": "把所有标记成黄色的电影全部看完清空。\n读完《每周工作四小时》。\n根据前哨战反馈调整表格。\n写完 10 篇公众号文章初稿。",
        "achievement": "",
        "reflection": "",
        "tags": ["学习", "工作"],
        "achievementLevel": 1
    },
    {
        "id": "diary-20250920",
        "date": "2025-09-20",
        "title": "成功日记 0920",
        "category": "学习阅读",
        "content": "完成 NCEE-CA。\n保持专注度 > 80%。\n完成 S 卷。\n观看《小约翰可汗的苏联大案》《科技补全》《凡人修仙传》。",
        "achievement": "",
        "reflection": "",
        "tags": ["学习", "阅读"],
        "achievementLevel": 3
    },
    {
        "id": "diary-20250919",
        "date": "2025-09-19",
        "title": "成功日记 0919",
        "category": "健身学习",
        "content": "早起完成晨间习惯。\n阅读 6+ 本书。\n冥想 6 分钟。\n平板支撑 1 分钟。\n看《老友记》S1E01。\n补充极客 AI 周刊内容。\n整理宿舍并加入人工智能协会。",
        "achievement": "",
        "reflection": "",
        "tags": ["健身", "学习", "阅读"],
        "achievementLevel": 3
    },
    {
        "id": "diary-20250918",
        "date": "2025-09-18",
        "title": "拥抱问题并保持饥渴感",
        "category": "创作学习",
        "content": "保证充足睡眠。\n持续为公众号创作并获得打赏。\n完成 NCEE-CA,拿到 74 分。\n提醒自己:容忍小麻烦才能成就大事。\n遇到问题时保持积极,并思考自己是在崩溃边缘还是突破前夕。",
        "achievement": "",
        "reflection": "容忍小麻烦才能成就大事。遇到问题时保持积极，思考自己是在崩溃边缘还是突破前夕。",
        "tags": ["创作", "学习", "健身"],
        "achievementLevel": 1
    },
    {
        "id": "diary-20250917",
        "date": "2025-09-17",
        "title": "小程序上线与成功日记成形",
        "category": "学习健身",
        "content": "完成个人小程序。\n录制日课 01。\n阅读 7 本书。\n23 点前早睡。\n把小确幸改造成成功日记系统。\n公众号文章为保证深度推迟到 27 号。\n节流拒绝不必要消费。",
        "achievement": "",
        "reflection": "",
        "tags": ["学习", "健身"],
        "achievementLevel": 3
    },
    {
        "id": "diary-20250916",
        "date": "2025-09-16",
        "title": "老王 Agent 1.0 与首次赞赏",
        "category": "学习阅读",
        "content": "搭建 laowang Agent 1.0。\n收到 Passion T-shirt。\n保持充足睡眠。\n人生首次收到公众号赞赏,激动又惊喜。",
        "achievement": "人生首次收到公众号赞赏",
        "reflection": "",
        "tags": ["学习", "阅读", "创作"],
        "achievementLevel": 5
    },
    {
        "id": "diary-20250915",
        "date": "2025-09-15",
        "title": "日课录制与浪潮纪念",
        "category": "学习阅读",
        "content": "跑步 3 公里。\n保证充足睡眠。\n公众号写作输出。\n录制高考 650+、日课、潮前先锋营 01、网站搭建指南四套课程。\n收到 Wave Ahead T 恤。",
        "achievement": "",
        "reflection": "",
        "tags": ["学习", "阅读", "创作"],
        "achievementLevel": 2
    },
    {
        "id": "diary-20250914",
        "date": "2025-09-14",
        "title": "Neuron 学习与理财自律",
        "category": "学习理财",
        "content": "学习 Neuron。\n续费 chatST。\n跑步 30 分钟。\n观看《前哨战》并用其优化飞书表格。\n保证充足睡眠。",
        "achievement": "",
        "reflection": "",
        "tags": ["学习", "理财"],
        "achievementLevel": 1
    },
    {
        "id": "diary-20250913",
        "date": "2025-09-13",
        "title": "持续迭代的学习日",
        "category": "学习影视",
        "content": "重温《小黑的奇幻冒险》。\n在云晨图书馆学习。\n决定把每日俯卧撑改为 10 组×3 次。\n高频迭代反思。\n坚持早睡。",
        "achievement": "",
        "reflection": "高频迭代反思",
        "tags": ["学习", "影视", "音乐"],
        "achievementLevel": 1
    },
    {
        "id": "diary-20250912",
        "date": "2025-09-12",
        "title": "内容创作与英文日记起步",
        "category": "学习影视",
        "content": "观看罗永浩广播和直播。\n写公众号文章。\n持续搭建个人网站。\n用英语记录每日成功日记的开端。",
        "achievement": "开始用英语记录成功日记",
        "reflection": "",
        "tags": ["学习", "影视", "创作"],
        "achievementLevel": 1
    }
]
